pylibxc
